{"paper_id": "e5acacc487270c0a4d682634bd15b8fbb337c2af", "title": "NOVA: An Agentic Framework for Automated Histopathology Analysis and Discovery", "year": 2025, "citation_count": 0, "reference_count": 0, "authors": [{"authorId": "2187496179", "name": "Anurag Vaidya"}, {"authorId": "2305486264", "name": "Felix Meissen"}, {"authorId": "2261277520", "name": "D. C. Castro"}, {"authorId": "82303325", "name": "Shruthi Bannur"}, {"authorId": "2126530861", "name": "Tristan Lazard"}, {"authorId": "25259989", "name": "Drew F. K. Williamson"}, {"authorId": "2285427160", "name": "F. Mahmood"}, {"authorId": "2029689505", "name": "Javier Alvarez-Valle"}, {"authorId": "2261608797", "name": "Stephanie L. Hyland"}, {"authorId": "2199938946", "name": "Kenza Bouzid"}]}