{"paper_id": "32d2ebe160a4305e524b7bc6e447b990246562cb", "title": "Geometric Prior-Guided Federated Prompt Calibration", "year": 2025, "citation_count": 0, "reference_count": 72, "authors": [{"authorId": "2329961013", "name": "Fei Luo"}, {"authorId": "2397923857", "name": "Ziwei Zhao"}, {"authorId": "2383087625", "name": "Mingxuan Wang"}, {"authorId": "2397425493", "name": "Duoyang Li"}, {"authorId": "2384393065", "name": "Zhe Qian"}, {"authorId": "2397379498", "name": "Jiayi Tuo"}, {"authorId": "2384313688", "name": "Chenyue Zhou"}, {"authorId": "2344148169", "name": "Yanbiao Ma"}]}