{"paper_id": "d960c2343db99b136a7b4423ae0cece28f112d6c", "title": "ALERT Open Dataset and Input-Size-Agnostic Vision Transformer for Driver Activity Recognition Using IR-UWB", "year": 2025, "citation_count": 0, "reference_count": 51, "authors": [{"authorId": "2355046709", "name": "Jeongjun Park"}, {"authorId": "2110796634", "name": "Sunwook Hwang"}, {"authorId": "2189880972", "name": "Hyeonho Noh"}, {"authorId": "2157358697", "name": "Jin Mo Yang"}, {"authorId": "2335151527", "name": "Hyun Jong Yang"}, {"authorId": "1682876", "name": "S. Bahk"}]}