{"paper_id": "4e9cc0fee2a9e8017f9f37e6d68368e4b3725e1b", "title": "A Threshold-Triggered Deep Q-Network-Based Framework for Self-Healing in Autonomic Software-Defined IIoT-Edge Networks", "year": 2025, "citation_count": 0, "reference_count": 55, "authors": [{"authorId": "2041284699", "name": "Agrippina Mwangi"}, {"authorId": "2326499040", "name": "León Navarro-Hilfiker"}, {"authorId": "2398905789", "name": "Lukasz Brewka"}, {"authorId": "2075025609", "name": "Mikkel Gryning"}, {"authorId": "2253619922", "name": "Elena Fumagalli"}, {"authorId": "2248593341", "name": "M. Gibescu"}]}