{"paper_id": "a5ba0be06be2198d0bfb057691d5ba82ef76a6fa", "title": "Evaluating the Clinical Impact of Generative Inpainting on Bone Age Estimation", "year": 2025, "citation_count": 0, "reference_count": 15, "authors": [{"authorId": "2277247803", "name": "F. A. Matsuoka"}, {"authorId": "2395537331", "name": "E. M. J. M. Farina"}, {"authorId": "2395534010", "name": "A. S. Serpa"}, {"authorId": "2395536549", "name": "Soraya Monteiro"}, {"authorId": "2395536142", "name": "Rodrigo Ragazzini"}, {"authorId": "2273487534", "name": "Nitamar Abdala"}, {"authorId": "2395841177", "name": "M. S. Takahashi"}, {"authorId": "2395534370", "name": "Felipe Kitamura"}]}