{"paper_id": "08027787c6b0796206dc78ad28d8e4b8c089ad6c", "title": "SCALE: Selective Resource Allocation for Overcoming Performance Bottlenecks in Mathematical Test-time Scaling", "year": 2025, "citation_count": 1, "reference_count": 24, "authors": [{"authorId": "2276752271", "name": "Yang Xiao"}, {"authorId": "2307074519", "name": "Chunpu Xu"}, {"authorId": "2273661632", "name": "Ruifeng Yuan"}, {"authorId": "2257134079", "name": "Jiashuo Wang"}, {"authorId": "2258788393", "name": "Wenjie Li"}, {"authorId": "2363559569", "name": "Pengfei Liu"}]}