{"paper_id": "8eb0630913261c6f53d87efc786de4caa282e065", "title": "Pillar-0: A New Frontier for Radiology Foundation Models", "year": 2025, "citation_count": 5, "reference_count": 53, "authors": [{"authorId": "2384365630", "name": "Kumar Krishna Agrawal"}, {"authorId": "2394146696", "name": "Longchao Liu"}, {"authorId": "2249587117", "name": "Long Lian"}, {"authorId": "2127612729", "name": "Michael Nercessian"}, {"authorId": "2264843870", "name": "Natalia Harguindeguy"}, {"authorId": "2394091023", "name": "Yufu Wu"}, {"authorId": "2243013270", "name": "Peter Mikhael"}, {"authorId": "2282018754", "name": "Gigin Lin"}, {"authorId": "144346741", "name": "L. Sequist"}, {"authorId": "2242367540", "name": "Florian J. Fintelmann"}, {"authorId": "2327334625", "name": "Trevor Darrell"}, {"authorId": "2349426965", "name": "Yutong Bai"}, {"authorId": "2350492049", "name": "Maggie Chung"}, {"authorId": "2281035913", "name": "A. Yala"}]}