{"paper_id": "94fbaf32a5beaae4b1b23f5fde7333774a09e653", "title": "LEAD: Minimizing Learner-Expert Asymmetry in End-to-End Driving", "year": 2025, "citation_count": 1, "reference_count": 58, "authors": [{"authorId": "2112399625", "name": "Long Nguyen"}, {"authorId": "2400418449", "name": "Micha Fauth"}, {"authorId": "2167151828", "name": "Bernhard Jaeger"}, {"authorId": "114959365", "name": "Daniel Dauner"}, {"authorId": "2325097476", "name": "Maximilian Igl"}, {"authorId": "2265966462", "name": "Andreas Geiger"}, {"authorId": "31352445", "name": "Kashyap Chitta"}]}