{"paper_id": "706ac11b05c7b0aca069f78d7b8f9a97f5704826", "title": "L2V-CoT: Cross-Modal Transfer of Chain-of-Thought Reasoning via Latent Intervention", "year": 2025, "citation_count": 1, "reference_count": 37, "authors": [{"authorId": "2330236473", "name": "Yu-Liang Zhan"}, {"authorId": "2109887979", "name": "Xinyu Tang"}, {"authorId": "2349809351", "name": "Han Wan"}, {"authorId": "2367256226", "name": "Jian Li"}, {"authorId": "2265728957", "name": "Ji-Rong Wen"}, {"authorId": "2391692289", "name": "Hao Sun"}]}