{"paper_id": "2b709201498db54f19d96f50ef61ac095d71c445", "title": "Efficient Diffusion Planning with Temporal Diffusion", "year": 2025, "citation_count": 0, "reference_count": 33, "authors": [{"authorId": "47093626", "name": "Jiaming Guo"}, {"authorId": "2349675131", "name": "Rui Zhang"}, {"authorId": "2277421923", "name": "Zerun Li"}, {"authorId": "2117957883", "name": "Yunkai Gao"}, {"authorId": "2072713784", "name": "Shaohui Peng"}, {"authorId": "2219976844", "name": "Siming Lan"}, {"authorId": "2109635961", "name": "Xingui Hu"}, {"authorId": "1678776", "name": "Zidong Du"}, {"authorId": "22066021", "name": "Xishan Zhang"}, {"authorId": "2319805216", "name": "Ling Li"}]}