{"paper_id": "bbc804623d0b7251003ac012c1974f39bca4f075", "title": "The More, the Merrier: Contrastive Fusion for Higher-Order Multimodal Alignment", "year": 2025, "citation_count": 0, "reference_count": 46, "authors": [{"authorId": "2168532069", "name": "Stefanos Koutoupis"}, {"authorId": "1471541199", "name": "M. Zervou"}, {"authorId": "2214303458", "name": "Konstantinos Kontras"}, {"authorId": "2304737756", "name": "M. D. Vos"}, {"authorId": "2366618823", "name": "Panagiotis Tsakalides"}, {"authorId": "2394311563", "name": "Grigorios Tsagatakis"}]}