{"paper_id": "f868781caddba19a3d07c4113882630c24f201b8", "title": "DialBench: Towards Accurate Reading Recognition of Pointer Meter using Large Foundation Models", "year": 2025, "citation_count": 0, "reference_count": 38, "authors": [{"authorId": "2299102129", "name": "Futian Wang"}, {"authorId": "2316634919", "name": "Chao Weng"}, {"authorId": "2341805040", "name": "Xiao Wang"}, {"authorId": "2117102108", "name": "Zhen Chen"}, {"authorId": "2193387840", "name": "Zhicheng Zhao"}, {"authorId": "2261757008", "name": "Jin Tang"}]}