{"paper_id": "31b8b84ee8c8958b92b564dbbbf8818d74f80e34", "title": "VisReason: A Large-Scale Dataset for Visual Chain-of-Thought Reasoning", "year": 2025, "citation_count": 2, "reference_count": 74, "authors": [{"authorId": "2328494738", "name": "Lingxiao Li"}, {"authorId": "2371128469", "name": "Yifan Wang"}, {"authorId": "2346647075", "name": "Xinyan Gao"}, {"authorId": "2394245724", "name": "Chen Tang"}, {"authorId": "2400730833", "name": "Xiangyu Yue"}, {"authorId": "2371076176", "name": "Chenyu You"}]}