{"paper_id": "25bd9c4409dbb64670f2b4f63db807ba1450b0db", "title": "SensHRPS: Sensing Comfortable Human-Robot Proxemics and Personal Space With Eye-Tracking", "year": 2025, "citation_count": 0, "reference_count": 28, "authors": [{"authorId": "2397491818", "name": "Nadezhda Kushina"}, {"authorId": "2397547587", "name": "Ko Watanabe"}, {"authorId": "16317875", "name": "A. Kannan"}, {"authorId": "2051807191", "name": "Ashita Ashok"}, {"authorId": "2257211369", "name": "Andreas Dengel"}, {"authorId": "2272891123", "name": "Karsten Berns"}]}