{"paper_id": "c05d2faf5bd07cc71ff20995f0cf677f77c8b4f6", "title": "FlexiFlow: decomposable flow matching for generation of flexible molecular ensemble", "year": 2025, "citation_count": 0, "reference_count": 50, "authors": [{"authorId": "2362947144", "name": "Riccardo Tedoldi"}, {"authorId": "2268590953", "name": "Ola Engkvist"}, {"authorId": "2062950823", "name": "P. Bryant"}, {"authorId": "2283308245", "name": "Hossein Azizpour"}, {"authorId": "2284772857", "name": "J. Janet"}, {"authorId": "2273854667", "name": "Alessandro Tibo"}]}