{"paper_id": "51cfea445e353dd22a2cd9e5a74d7172dae3158e", "title": "Derivative-Informed Fourier Neural Operator: Universal Approximation and Applications to PDE-Constrained Optimization", "year": 2025, "citation_count": 1, "reference_count": 0, "authors": [{"authorId": "2321992781", "name": "Boyuan Yao"}, {"authorId": "2153294961", "name": "Dingcheng Luo"}, {"authorId": "1861527147", "name": "Lianghao Cao"}, {"authorId": "51219644", "name": "Nikola B. Kovachki"}, {"authorId": "2345271752", "name": "Thomas O'Leary-Roseberry"}, {"authorId": "2303841470", "name": "Omar Ghattas"}]}