{"paper_id": "53eae563f50365b92e16f94b54891fa86fa14055", "title": "Emergent temporal abstractions in autoregressive models enable hierarchical reinforcement learning", "year": 2025, "citation_count": 1, "reference_count": 0, "authors": [{"authorId": "51194506", "name": "Seijin Kobayashi"}, {"authorId": "2366019620", "name": "Yanick Schimpf"}, {"authorId": "2239102711", "name": "Maximilian Schlegel"}, {"authorId": "2237805637", "name": "Angelika Steger"}, {"authorId": "2276436804", "name": "Maciej Wolczyk"}, {"authorId": "145167136", "name": "J. Oswald"}, {"authorId": "1742339548", "name": "Nino Scherrer"}, {"authorId": "29993414", "name": "Kaitlin Maile"}, {"authorId": "2287810628", "name": "Guillaume Lajoie"}, {"authorId": "2287807305", "name": "Blake A. Richards"}, {"authorId": "2278009", "name": "R. Saurous"}, {"authorId": "2254252286", "name": "J. Manyika"}, {"authorId": "2661025", "name": "B. A. Y. Arcas"}, {"authorId": "1753618449", "name": "Alexander Meulemans"}, {"authorId": "2276434301", "name": "João Sacramento"}]}