{"paper_id": "dc4a1e7a6a34bc3b12241e29afb3aed68f32922d", "title": "Closed-Loop Robotic Manipulation of Transparent Substrates for Self-Driving Laboratories using Deep Learning Micro-Error Correction", "year": 2025, "citation_count": 0, "reference_count": 58, "authors": [{"authorId": "2397375794", "name": "Kelsey Fontenot"}, {"authorId": "2397375746", "name": "Anjali Gorti"}, {"authorId": "2397380027", "name": "I. Goel"}, {"authorId": "6018731", "name": "T. Buonassisi"}, {"authorId": "2045775231", "name": "Alexander E. Siemenn"}]}