{"paper_id": "cb376523164d850aa4794561d59ffdf559576dcb", "title": "Dripper: Token-Efficient Main HTML Extraction with a Lightweight LM", "year": 2025, "citation_count": 2, "reference_count": 45, "authors": [{"authorId": "2306139062", "name": "Mengjie Liu"}, {"authorId": "2233445161", "name": "Jiahui Peng"}, {"authorId": "2288188121", "name": "Pei Chu"}, {"authorId": "2289911484", "name": "Jiantao Qiu"}, {"authorId": "2299118979", "name": "Ren Ma"}, {"authorId": "2375401201", "name": "He Zhu"}, {"authorId": "2362724698", "name": "Rui Min"}, {"authorId": "2290136213", "name": "Lindong Lu"}, {"authorId": "2288262004", "name": "Wenchang Ning"}, {"authorId": "2393886762", "name": "Linfeng Hou"}, {"authorId": "2293560297", "name": "Kaiwen Liu"}, {"authorId": "2288231452", "name": "Yuan Qu"}, {"authorId": "2290966898", "name": "Zhenxiang Li"}, {"authorId": "2393531365", "name": "Chao Xu"}, {"authorId": "2289992992", "name": "Zhongying Tu"}, {"authorId": "2382046022", "name": "Wentao Zhang"}, {"authorId": "2267889334", "name": "Conghui He"}]}