{"paper_id": "51b50ae545087990cbff7cbc61c4b274bf151ef9", "title": "BeHGAN: Bengali Handwritten Word Generation from Plain Text Using Generative Adversarial Networks", "year": 2025, "citation_count": 0, "reference_count": 27, "authors": [{"authorId": "2288113728", "name": "Md. Rakibul Islam"}, {"authorId": "2287974779", "name": "Md. Kamrozzaman Bhuiyan"}, {"authorId": "2401262193", "name": "Safwan Muntasir"}, {"authorId": "2401262296", "name": "Arifur Rahman Jawad"}, {"authorId": "2341537787", "name": "Most. Sharmin Sultana Samu"}]}