{"paper_id": "17c1b416246aa1702e1b8b24395f992a1a5a1e6c", "title": "SurgMLLMBench: A Multimodal Large Language Model Benchmark Dataset for Surgical Scene Understanding", "year": 2025, "citation_count": 1, "reference_count": 30, "authors": [{"authorId": "2331417396", "name": "Tae-Min Choi"}, {"authorId": "2376190810", "name": "Tae Kyeong Jeong"}, {"authorId": "2380573758", "name": "Garam Kim"}, {"authorId": "2108479799", "name": "Jaemin Lee"}, {"authorId": "2345273772", "name": "Yeongyoon Koh"}, {"authorId": "22264761", "name": "In Cheul Choi"}, {"authorId": "2338057177", "name": "Jae-ho Chung"}, {"authorId": "2397345825", "name": "Jong Woong Park"}, {"authorId": "2380550975", "name": "Juyoun Park"}]}