{"paper_id": "49682525d1fc3d1450a1762f04d9f61f37e06064", "title": "Environment-Aware Channel Inference via Cross-Modal Flow: From Multimodal Sensing to Wireless Channels", "year": 2025, "citation_count": 0, "reference_count": 41, "authors": [{"authorId": "2331323246", "name": "Guangming Liang"}, {"authorId": "2331394951", "name": "Mingjie Yang"}, {"authorId": "10747375", "name": "Dongzhu Liu"}, {"authorId": "2282971462", "name": "Paul Henderson"}, {"authorId": "2305671813", "name": "Lajos Hanzo"}]}