{"paper_id": "8330cfb504ac3f7e4dd365ba777f5a4919eb8287", "title": "FANoise: Singular Value-Adaptive Noise Modulation for Robust Multimodal Representation Learning", "year": 2025, "citation_count": 0, "reference_count": 54, "authors": [{"authorId": "2394491893", "name": "Jiaoyang Li"}, {"authorId": "2397574168", "name": "Jun Fang"}, {"authorId": "2316174511", "name": "Tian Gao"}, {"authorId": "2284701992", "name": "Xiaohui Zhang"}, {"authorId": "2394351737", "name": "Zhiyuan Liu"}, {"authorId": "2187677598", "name": "Chao Liu"}, {"authorId": "2394678697", "name": "Pengzhang Liu"}, {"authorId": "2374185281", "name": "Qixia Jiang"}]}