{"paper_id": "6ea21d681633f11ed43e928dfb583d47449ededb", "title": "VCU-Bridge: Hierarchical Visual Connotation Understanding via Semantic Bridging", "year": 2025, "citation_count": 2, "reference_count": 48, "authors": [{"authorId": "2394076886", "name": "Ming Zhong"}, {"authorId": "2391801349", "name": "Yuanlei Wang"}, {"authorId": "2391651655", "name": "Liuzhou Zhang"}, {"authorId": "2394083696", "name": "Arctanx An"}, {"authorId": "2392811044", "name": "Renrui Zhang"}, {"authorId": "2395595475", "name": "Hao Liang"}, {"authorId": "2376430497", "name": "Ming Lu"}, {"authorId": "2384068216", "name": "Ying Shen"}, {"authorId": "2362515410", "name": "Wentao Zhang"}]}