{"paper_id": "4d7eabcd10e17c300239337bca56abe024961a53", "title": "Does Understanding Inform Generation in Unified Multimodal Models? From Analysis to Path Forward", "year": 2025, "citation_count": 3, "reference_count": 53, "authors": [{"authorId": "2350309448", "name": "Yuwei Niu"}, {"authorId": "2386087474", "name": "Weiyang Jin"}, {"authorId": "2315613899", "name": "Jiaqi Liao"}, {"authorId": "2304272440", "name": "Chaoran Feng"}, {"authorId": "2331175560", "name": "Peng Jin"}, {"authorId": "2364211315", "name": "Bin Lin"}, {"authorId": "2319391152", "name": "Zongjian Li"}, {"authorId": "2256419313", "name": "Bin Zhu"}, {"authorId": "2360539226", "name": "Weihao Yu"}, {"authorId": "2307561441", "name": "Li Yuan"}]}