{"paper_id": "f790083a2881b4410628728345b720f36d334630", "title": "Statistical laws and linguistics inform meaning in naturalistic and fictional conversation", "year": 2025, "citation_count": 0, "reference_count": 0, "authors": [{"authorId": "2335558437", "name": "Ashley M. A. Fehr"}, {"authorId": "2331175585", "name": "Calla Beauregard"}, {"authorId": "2217324257", "name": "J. Zimmerman"}, {"authorId": "2406817834", "name": "Katie Ekström"}, {"authorId": "2390487388", "name": "Pablo Rosillo-Rodes"}, {"authorId": "2274229653", "name": "Christopher M. Danforth"}, {"authorId": "2296225420", "name": "P. Dodds"}]}