{"paper_id": "d144a8369b84cbabf7933463d2e645d0067eea66", "title": "DiverseGRPO: Mitigating Mode Collapse in Image Generation via Diversity-Aware GRPO", "year": 2025, "citation_count": 3, "reference_count": 30, "authors": [{"authorId": "2374406138", "name": "Henglin Liu"}, {"authorId": "2401667114", "name": "Huijuan Huang"}, {"authorId": "2387955122", "name": "Jing Wang"}, {"authorId": "2372571650", "name": "Chang Liu"}, {"authorId": "2307894621", "name": "Xiu Li"}, {"authorId": "2305263249", "name": "Xiangyang Ji"}]}