{"paper_id": "347b24e900c85e067f03e7dc82428bd0f944438b", "title": "ByteLoom: Weaving Geometry-Consistent Human-Object Interactions through Progressive Curriculum Learning", "year": 2025, "citation_count": 1, "reference_count": 47, "authors": [{"authorId": "2299262124", "name": "Bangya Liu"}, {"authorId": "2392598465", "name": "Xinyu Gong"}, {"authorId": "2400361893", "name": "Zelin Zhao"}, {"authorId": "2400353634", "name": "Ziyang Song"}, {"authorId": "2376414400", "name": "Yulei Lu"}, {"authorId": "2376360794", "name": "Suhui Wu"}, {"authorId": "2376420699", "name": "Jun Zhang"}, {"authorId": "2321041564", "name": "Suman Banerjee"}, {"authorId": "2377273141", "name": "Hao Zhang"}]}