{"paper_id": "6f5ce7280a80e1ab4c6bce893818e58f0e18d70b", "title": "Few-Shot Inference of Human Perceptions of Robot Performance in Social Navigation Scenarios", "year": 2025, "citation_count": 0, "reference_count": 63, "authors": [{"authorId": "2211068102", "name": "Qiping Zhang"}, {"authorId": "39282796", "name": "Nathan Tsoi"}, {"authorId": "2230205764", "name": "Mofeed Nagib"}, {"authorId": "2259956020", "name": "Hao-Tien Lewis Chiang"}, {"authorId": "2399165940", "name": "Marynel V'azquez"}]}