{"paper_id": "a37cea825dec002b91a549eacaf18558780832ad", "title": "AutoLink: Autonomous Schema Exploration and Expansion for Scalable Schema Linking in Text-to-SQL at Scale", "year": 2025, "citation_count": 1, "reference_count": 32, "authors": [{"authorId": "2368685657", "name": "Ziyang Wang"}, {"authorId": "2328974422", "name": "Yuanlei Zheng"}, {"authorId": "2329909445", "name": "Zhenbiao Cao"}, {"authorId": "2275116857", "name": "Xiaojin Zhang"}, {"authorId": "2373573595", "name": "Zhongyu Wei"}, {"authorId": "2381259557", "name": "Pei Fu"}, {"authorId": "2363405807", "name": "Zhenbo Luo"}, {"authorId": "2373981426", "name": "Wei Chen"}, {"authorId": "2261455485", "name": "Xiang Bai"}]}