{"paper_id": "3799348f1bfb351d85204b81b4f779b4271f4b42", "title": "OPOR-Bench: Evaluating Large Language Models on Online Public Opinion Report Generation", "year": 2025, "citation_count": 2, "reference_count": 100, "authors": [{"authorId": "2351767026", "name": "Jinzheng Yu"}, {"authorId": "2395689804", "name": "Yang Xu"}, {"authorId": "2267193978", "name": "Haozhen Li"}, {"authorId": "2108994381", "name": "Junqi Li"}, {"authorId": "2290619980", "name": "Yifan Feng"}, {"authorId": "2367745700", "name": "Ligu Zhu"}, {"authorId": "2395684950", "name": "Hao Shen"}, {"authorId": "2395688439", "name": "Lei Shi"}]}