{"paper_id": "83b005230e57d632aabc2d8ea22ee8e283bf2261", "title": "Thinking Forward and Backward: Multi-Objective Reinforcement Learning for Retrieval-Augmented Reasoning", "year": 2025, "citation_count": 0, "reference_count": 49, "authors": [{"authorId": "2294541116", "name": "Wenda Wei"}, {"authorId": "2143860482", "name": "Yuansan Liu"}, {"authorId": "2109960367", "name": "Ruqing Zhang"}, {"authorId": "2316783018", "name": "Jiafeng Guo"}, {"authorId": "2069859063", "name": "Lixin Su"}, {"authorId": "2237948548", "name": "Shuaiqiang Wang"}, {"authorId": "2331316040", "name": "Dawei Yin"}, {"authorId": "2265490493", "name": "M. D. Rijke"}, {"authorId": "2244825947", "name": "Xueqi Cheng"}]}