{"paper_id": "6bea73e482df128502c6c96b0c27f3a4b8067f61", "title": "SINRL: Socially Integrated Navigation with Reinforcement Learning using Spiking Neural Networks", "year": 2025, "citation_count": 0, "reference_count": 29, "authors": [{"authorId": "2397374231", "name": "Florian Tretter"}, {"authorId": "2281043320", "name": "Daniel Flögel"}, {"authorId": "113589974", "name": "Alexandru Vasilache"}, {"authorId": "2240521250", "name": "Max Grobbel"}, {"authorId": "2381996676", "name": "Jürgen Becker"}, {"authorId": "2295518208", "name": "Sören Hohmann"}]}