{"paper_id": "3274a0e3351a506c78fb128918a8479e349d606d", "title": "OPV: Outcome-based Process Verifier for Efficient Long Chain-of-Thought Verification", "year": 2025, "citation_count": 2, "reference_count": 25, "authors": [{"authorId": "2283840256", "name": "Zijian Wu"}, {"authorId": "2401119867", "name": "Lingkai Kong"}, {"authorId": "2266359401", "name": "Wenwei Zhang"}, {"authorId": "2335827751", "name": "Songyang Gao"}, {"authorId": "2293825807", "name": "Yuzhe Gu"}, {"authorId": "2378094163", "name": "Zhongrui Cai"}, {"authorId": "2400506195", "name": "Tianyou Ma"}, {"authorId": "2397921680", "name": "Yuhong Liu"}, {"authorId": "2108389227", "name": "Zhi Wang"}, {"authorId": "2293667675", "name": "Runyuan Ma"}, {"authorId": "2398226551", "name": "Guangyu Wang"}, {"authorId": "2310775847", "name": "Wei Li"}, {"authorId": "2267889334", "name": "Conghui He"}, {"authorId": "2261095726", "name": "Dahua Lin"}, {"authorId": "2371440263", "name": "Kai Chen"}]}