{"paper_id": "628dcc7046ea462b5e770a0f070c5b0988aaeee0", "title": "Towards a Science of Scaling Agent Systems", "year": 2025, "citation_count": 30, "reference_count": 60, "authors": [{"authorId": "2107937893", "name": "Y. Kim"}, {"authorId": "2366015412", "name": "Ken Gu"}, {"authorId": "2298091351", "name": "Chanwoo Park"}, {"authorId": "2298953061", "name": "Chunjong Park"}, {"authorId": "2370716973", "name": "Samuel Schmidgall"}, {"authorId": "2060748022", "name": "A. Heydari"}, {"authorId": "2398243183", "name": "Yao Yan"}, {"authorId": "2343274458", "name": "Zhihan Zhang"}, {"authorId": "8103389", "name": "Yuchen Zhuang"}, {"authorId": "2305740425", "name": "Yun Liu"}, {"authorId": "2305611512", "name": "Mark Malhotra"}, {"authorId": "2351606035", "name": "Paul Pu Liang"}, {"authorId": "2329047452", "name": "Hae Won Park"}, {"authorId": "2326446572", "name": "Yuzhe Yang"}, {"authorId": "2268804791", "name": "Xuhai Xu"}, {"authorId": "2208893533", "name": "Yi-qing Du"}, {"authorId": "2261277652", "name": "Shwetak N. Patel"}, {"authorId": "2316432491", "name": "Tim Althoff"}, {"authorId": "2315286830", "name": "D. McDuff"}, {"authorId": "2267683550", "name": "Xin Liu"}]}