{"paper_id": "06aaa87f8a6a002cc3ed695cd0c92094d65f9320", "title": "EXR: An Interactive Immersive EHR Visualization in Extended Reality", "year": 2025, "citation_count": 0, "reference_count": 49, "authors": [{"authorId": "2080363233", "name": "B. Marteau"}, {"authorId": "2358773369", "name": "Shaun Q. Y. Tan"}, {"authorId": "2269410192", "name": "Jieru Li"}, {"authorId": "2167127702", "name": "Andrew Hornback"}, {"authorId": "2195947297", "name": "Yishan Zhong"}, {"authorId": "2397284110", "name": "Shaunna Wang"}, {"authorId": "2333826579", "name": "Christian Lowson"}, {"authorId": "2333825284", "name": "Jason Woloff"}, {"authorId": "8538840", "name": "J. Pahys"}, {"authorId": "2366006046", "name": "Steven W. Hwang"}, {"authorId": "2004361939", "name": "Coleman Hilton"}, {"authorId": "2359489164", "name": "May D. Wang"}]}