{"paper_id": "18b1792f789f695b6a69229cd6a67cca99055307", "title": "Rethinking Retrieval: From Traditional Retrieval Augmented Generation to Agentic and Non-Vector Reasoning Systems in the Financial Domain for Large Language Models", "year": 2025, "citation_count": 0, "reference_count": 35, "authors": [{"authorId": "2326836585", "name": "Elias Lumer"}, {"authorId": "2393204760", "name": "Matt Melich"}, {"authorId": "2357967269", "name": "Olivia Zino"}, {"authorId": "2394091335", "name": "Elena Kim"}, {"authorId": "2393206258", "name": "Sara Dieter"}, {"authorId": "2327043776", "name": "Pradeep Honaganahalli Basavaraju"}, {"authorId": "2327043802", "name": "V. K. Subbiah"}, {"authorId": "2327181836", "name": "James A. Burke"}, {"authorId": "2393401740", "name": "Roberto Hernandez"}]}