{"paper_id": "9c6b33e398d8160e30442711c3597fd1dcd27a66", "title": "Brain-MGF: Multimodal Graph Fusion Network for EEG-fMRI Brain Connectivity Analysis Under Psilocybin", "year": 2025, "citation_count": 0, "reference_count": 25, "authors": [{"authorId": "145184869", "name": "S. Yap"}, {"authorId": "51466331", "name": "Fuad M. Noman"}, {"authorId": "152361175", "name": "J. Loo"}, {"authorId": "2146178583", "name": "D. Stoliker"}, {"authorId": "34606412", "name": "Moein Khajehnejad"}, {"authorId": "2240174978", "name": "R. Phan"}, {"authorId": "1745871", "name": "D. Dowe"}, {"authorId": "2275168419", "name": "Adeel Razi"}, {"authorId": "2267556725", "name": "Chee-Ming Ting"}]}