{"paper_id": "4e13c7029681cf8010ddd53fc68ca987085b1f9e", "title": "MINES: Explainable Anomaly Detection through Web API Invariant Inference", "year": 2025, "citation_count": 0, "reference_count": 70, "authors": [{"authorId": "2332296171", "name": "Wenjie Zhang"}, {"authorId": "2312343648", "name": "Yun Lin"}, {"authorId": "2397380991", "name": "Chun Fung Amos Kwok"}, {"authorId": "2312305564", "name": "Xiwen Teoh"}, {"authorId": "2290172332", "name": "Xiao-Ping Xie"}, {"authorId": "2332350883", "name": "F. Liauw"}, {"authorId": "2340190780", "name": "Hongyu Zhang"}, {"authorId": "2301410525", "name": "J. Dong"}]}