{"paper_id": "e898bb88dc7c1b6eb108f381b80f02588c24cf32", "title": "Closing the Train-Test Gap in World Models for Gradient-Based Planning", "year": 2025, "citation_count": 2, "reference_count": 74, "authors": [{"authorId": "2149945872", "name": "Arjun Parthasarathy"}, {"authorId": "1907493959", "name": "Nimit Kalra"}, {"authorId": "2344755157", "name": "Rohun Agrawal"}, {"authorId": "2270469816", "name": "Yann LeCun"}, {"authorId": "1388839835", "name": "Oumayma Bounou"}, {"authorId": "2397615886", "name": "Pavel Izmailov"}, {"authorId": "2126058635", "name": "Micah Goldblum"}]}